mluu/__init__.py
mluu-0.1.dist-info/LICENSE
mluu-0.1.dist-info/METADATA
mluu-0.1.dist-info/WHEEL
mluu-0.1.dist-info/top_level.txt
mluu-0.1.dist-info/RECORD
