Metadata-Version: 2.1
Name: mluu
Version: 0.1
Summary: A funny joke
Home-page: https://github.com/minhl/mluu
Author: Minh Luu
Author-email: minhl@toll.com.au
License: Private
Platform: UNKNOWN
Classifier: Programming Language :: Python :: 3
Classifier: License :: OSI Approved :: MIT License
Classifier: Operating System :: OS Independent
